rationalpy/__init__.py
rationalpy/rational_array.py
rationalpy/rational_array_class.py
rationalpy-0.1.2.post1.dist-info/METADATA
rationalpy-0.1.2.post1.dist-info/WHEEL
rationalpy-0.1.2.post1.dist-info/licenses/LICENSE
rationalpy-0.1.2.post1.dist-info/RECORD
